ap_validator/__init__.py
ap_validator/app_package.py
ogc_ap_validator-0.5.0.data/scripts/ap-validator
ogc_ap_validator-0.5.0.dist-info/METADATA
ogc_ap_validator-0.5.0.dist-info/WHEEL
ogc_ap_validator-0.5.0.dist-info/top_level.txt
ogc_ap_validator-0.5.0.dist-info/RECORD
