Metadata-Version: 2.1
Name: ogc-ap-validator
Version: 0.5.0
Summary: Validation tool to check OGC compliance of CWL files for application packages
License: Apache License, Version 2.0
Project-URL: Documentation, https://github.com/EOEPCA/app-package-validation/blob/main/README.md
Project-URL: Source, https://github.com/EOEPCA/app-package-validation/
Project-URL: Tracker, https://github.com/EOEPCA/app-package-validation/issues
Keywords: application package,CWL,validator,validation,OGC
Requires-Dist: requests
Requires-Dist: cwltool
Requires-Dist: click
Requires-Dist: loguru
